MANIFEST.in
README.md
example notebook.ipynb
license.md
pytest.ini
setup.cfg
setup.py
src/wisdom_of_crowds.py
src/wisdom_of_crowds.egg-info/PKG-INFO
src/wisdom_of_crowds.egg-info/SOURCES.txt
src/wisdom_of_crowds.egg-info/dependency_links.txt
src/wisdom_of_crowds.egg-info/requires.txt
src/wisdom_of_crowds.egg-info/top_level.txt
tests/test_wisdom_of_crowds.py
tests/tests.sh
tests/.reports/coverage-badge.svg
tests/.reports/tests-badge.svg